{
  "brandHeaderInfo": {
    "frankMullerHeadInfo": "Franck Muller is world-famous for its Grand Complications and Luxury watches. Discover all the Franck Muller Haute Horlogerie timepieces."
  },
  "products": [
    {
      "frankMuller": [
        {
          "id": 1,
          "brand": "Franck Muller",
          "name": "Vanguard 8880",
          "price": 35,
          "imgSrc": "fm_8880.jpg"
        },
        {
          "id": 2,
          "brand": "Franck Muller",
          "name": "Vanguard 8888",
          "price": 50,
          "imgSrc": "fm_8888.jpg"
        },
        {
          "id": 3,
          "brand": "Franck Muller",
          "name": "Vanguard 50",
          "price": 60,
          "imgSrc": "fm_vanguard_yachting.jpg"
        },
        {
          "id": 4,
          "brand": "Franck Muller",
          "name": "Vanguard YT75",
          "price": 60,
          "imgSrc": "fm_v50.jpg"
        }
      ]
    }
  ]
}
